{"mainGrids": [
    {
      "title": "Makeup products",
      "image": "/images/Grid/main Grid/M1.jpg",
      "link": "/search-results/mobile"
    },
    {
      "title": "New looks for the new season",
      "image": "/images/Grid/main Grid/M2.jpg",
      "link": "/search-results/makeup products"
    },
    {
      "title": "Do up your home",
      "image": "/images/Grid/main Grid/M3.jpg",
      "link": "/search-results/home products"
    },
    {
      "title": "Smart gadgets by Amazon",
      "image": "/images/Grid/main Grid/M4.jpg",
      "link": "/search-results/tv"
    }
  ]
}
